{
    "id": 10565740,
    "name": "Bloodbath",
    "author": "Riot",
    "creators": ["Asonicmen" , "Evasium" , "Crack" , "Riot" , "GgB0y" , "Michigun" , "Etzer" , "Giron" , "Havok" , "weoweoteo" , "Vermillion"],
    "verifier": "Edgar214",
    "verification": "https://www.youtube.com/watch?v=mmyBDeRqy0w",
    "percentToQualify": "100",
    "password": "Free To Copy",
    "descripcion": "Uno de los extremes más populares del juego y segundo nivel de la Apocalyptic Trilogy. En su momento fue considerado el top 1 por sus secciones de nave casi imposibles, y hoy sigue siendo un nivel bastante duro, con la parte de Michigun vista por muchos como la más complicada de todas. ",
    "records": [
        {
            "user": "RaymanNinja",
            "link": "https://www.youtube.com/watch?v=nAm4Pb-LHdw&list=PLTAVj4jn6Ls8MUByyyaGgyEmm370Em-iK&index=7",
            "percent": 100,
            "hz": 280
        },
        {
            "user": "KenethGD",
            "link": "https://www.youtube.com/watch?v=3FJZFnp1tCo",
            "percent": 100,
            "hz": 144
        },
        {
            "user": "venomioo",
            "link": "https://www.youtube.com/watch?v=lMYV6HvSI2s",
            "percent": 100,
            "hz": 240
        },
        {
            "user": "Danolex",
            "link": "https://www.youtube.com/watch?v=-Gpw2ZplDNk",
            "percent": 100,
            "hz": 360
        },
        {
            "user": "Katdann",
            "link": "https://www.youtube.com/watch?v=Z7W3_d4AkKA",
            "percent": 100,
            "hz": 244
        },
        {
            "user": "Blue",
            "link": "https://www.youtube.com/watch?v=z9pDJsxUhxo",
            "percent": 100,
            "hz": 240
        },
        {
            "user": "MarioPro",
            "link": "https://www.youtube.com/watch?v=nWfWd0yMbuI",
            "percent": 100,
            "hz": 360
        },
        {
            "user": "JPnabo",
            "link": "https://www.youtube.com/watch?v=HQBz0mzSvXU",
            "percent": 100,
            "hz": 144
        },
        {
            "user": "Jampy12",
            "link": "https://www.youtube.com/watch?v=GV6vZ2YLL5o",
            "percent": 100,
            "hz": 60
        },
        {
            "user": "Pachi",
            "link": "https://www.youtube.com/watch?v=Kw1RAolB8ek",
            "percent": 100,
            "hz": 144
        },
        {
            "user": "ItzNixo",
            "link": "https://www.youtube.com/watch?v=wo5G4bPd60k",
            "percent": 100,
            "hz": 240
        },
        {
            "user": "Zephyr",
            "link": "https://www.youtube.com/watch?v=ys9ub0jk05Y",
            "percent": 100,
            "hz": 576
        },
        {
            "user": "EABH",
            "link": "https://www.youtube.com/watch?v=gibXHOdh3oM",
            "percent": 100,
            "hz": 120
        }
    ]
}







