{
    "id": 30194711,
    "name": "Niflheim",
    "author": "Vismuth",
    "creators": ["Vismuth"],
    "verifier": "Zephyr",
    "verification": "https://www.youtube.com/watch?v=6nwBBALD9ek",
    "percentToQualify": "100",
    "password": "Free to copy",
    "records": [
        {
            "user": "Victor71GD",
            "link": "https://www.youtube.com/watch?v=JloZ_0F9sXQ&list=PLr0qrv4wwHD-j207Pg7dT4_iKXlwcrrOH&index=3",
            "percent": 100,
            "hz": 120,
            "mobile": true
        }
    ]
}
