{
    "id": 83825373,
    "name": "Overtime",
    "author": "KlaurosssS",
    "creators": ["Ji" , "Vyzion" , "UltraS4" , "WaRiox" , "Ellisha" , "ISSLOL" , "KlaurosssS" , "N3moProd" , "rZary_" , "Retro Head" , "Hir0shi" , "LaserSword33" , "Airtime [GD]" , "AbysS"],
    "verifier": "Jampy12",
    "verification": "https://www.youtube.com/watch?v=LuL68R-CP0c",
    "percentToQualify": "100",
    "password": "Free to copy",
     "description": "Overtime es un Extreme Demon en formato megacollab creado por KlaurosssS, N3mo y varios creadores más, verificado por Dorami y construido originalmente en solo dos días de mega swap antes de ser retrabajado durante semanas. Destaca por su jugabilidad rápida y muy dinámica, con gran énfasis en efectos visuales sincronizados con la canción Overtime de Cash Cash, transiciones constantes entre modos y secciones que mezclan ritmo intenso con momentos de lectura complicada. Es visto como un “work demon” moderno, muy espectacular a nivel de efectos y fluidez, pero con un balance de dificultad desbalanceado que puede hacer que los intentos avanzados se sientan tensos y desgastantes.",
    "records": [
    ]
}
